odoo/addons/mrp_workorder_sequence/README.rst
odoo/addons/mrp_workorder_sequence/__init__.py
odoo/addons/mrp_workorder_sequence/__manifest__.py
odoo/addons/mrp_workorder_sequence/i18n/mrp_workorder_sequence.pot
odoo/addons/mrp_workorder_sequence/models/__init__.py
odoo/addons/mrp_workorder_sequence/models/mrp_production.py
odoo/addons/mrp_workorder_sequence/models/mrp_workorder.py
odoo/addons/mrp_workorder_sequence/readme/CONTRIBUTORS.rst
odoo/addons/mrp_workorder_sequence/readme/DESCRIPTION.rst
odoo/addons/mrp_workorder_sequence/readme/USAGE.rst
odoo/addons/mrp_workorder_sequence/static/description/icon.png
odoo/addons/mrp_workorder_sequence/static/description/index.html
odoo/addons/mrp_workorder_sequence/views/mrp_workorder_view.xml
odoo14_addon_mrp_workorder_sequence-14.0.1.0.1.dist-info/METADATA
odoo14_addon_mrp_workorder_sequence-14.0.1.0.1.dist-info/WHEEL
odoo14_addon_mrp_workorder_sequence-14.0.1.0.1.dist-info/top_level.txt
odoo14_addon_mrp_workorder_sequence-14.0.1.0.1.dist-info/RECORD
